pipecat_tools/__init__.py
pipecat_tools/cli.py
pipecat_tools/core/__init__.py
pipecat_tools/core/consts.py
pipecat_tools/core/management.py
pipecat_tools/core/tool_manager.py
pipecat_tools/tools/__init__.py
pipecat_tools/tools/call_management.py
pipecat_tools/tools/scheduling.py
spacestep_tools-0.1.5.dist-info/licenses/LICENSE
tests/__init__.py
tests/test_basic_functionality.py
spacestep_tools-0.1.5.dist-info/METADATA
spacestep_tools-0.1.5.dist-info/WHEEL
spacestep_tools-0.1.5.dist-info/entry_points.txt
spacestep_tools-0.1.5.dist-info/top_level.txt
spacestep_tools-0.1.5.dist-info/RECORD
